sqlbucket/__init__.py
sqlbucket/cli.py
sqlbucket/core.py
sqlbucket/exceptions.py
sqlbucket/integrity.py
sqlbucket/project.py
sqlbucket/runners.py
sqlbucket/utils.py
sqlbucket/macros/aggregations.jinja2
sqlbucket/macros/common.jinja2
sqlbucket/template/config.yaml
sqlbucket/template/integrity/integrity_one.sql
sqlbucket/template/queries/query_one.sql
sqlbucket/template/queries/query_two.sql
sqlbucket-0.4.4.dist-info/LICENSE
sqlbucket-0.4.4.dist-info/METADATA
sqlbucket-0.4.4.dist-info/WHEEL
sqlbucket-0.4.4.dist-info/top_level.txt
sqlbucket-0.4.4.dist-info/RECORD
