Metadata-Version: 2.1
Name: sqlbucket
Version: 0.4.4
Summary: SQLBucket - Write your SQL ETL flow and ETL integrity tool.
Author-email: Philippe Oger <phil.oger@gmail.com>
License: MIT License
Project-URL: Homepage, https://github.com/socialpoint-labs/sqlbucket
Keywords: sql,etl,data-integrity
Classifier: Programming Language :: Python
Classifier: Programming Language :: Python :: 3
Classifier: License :: OSI Approved :: MIT License
Classifier: Operating System :: OS Independent
Classifier: Development Status :: 3 - Alpha
Classifier: Intended Audience :: Developers
Classifier: Intended Audience :: End Users/Desktop
Classifier: Intended Audience :: Science/Research
Classifier: Topic :: Database :: Front-Ends
Classifier: Topic :: Software Development :: Libraries :: Python Modules
Requires-Python: >=3.10
License-File: LICENSE
Requires-Dist: click (==8.1.3)
Requires-Dist: Jinja2 (==3.1.2)
Requires-Dist: MarkupSafe (==2.1.1)
Requires-Dist: PyYAML (==6.0)
Requires-Dist: SQLAlchemy (==1.4.44)
Requires-Dist: tabulate (==0.9.0)
Provides-Extra: dev
Requires-Dist: pytest (>=4) ; extra == 'dev'
Requires-Dist: coverage ; extra == 'dev'
